{
  "hooks": {
    "SessionStart": [
      {
        "matcher": "startup|resume|compact",
        "hooks": [
          {
            "type": "command",
            "command": "node dist/hooks/session-start.js",
            "timeout": 5
          }
        ]
      }
    ],
    "PostToolUse": [
      {
        "matcher": "Edit|Write|NotebookEdit",
        "hooks": [
          {
            "type": "command",
            "command": "node dist/hooks/post-tool-use.js",
            "timeout": 5
          }
        ]
      }
    ],
    "Stop": [
      {
        "hooks": [
          {
            "type": "command",
            "command": "node dist/hooks/stop.js",
            "timeout": 30
          }
        ]
      }
    ],
    "PreCompact": [
      {
        "hooks": [
          {
            "type": "command",
            "command": "node dist/hooks/pre-compact.js",
            "timeout": 30
          }
        ]
      }
    ]
  }
}
